scutil/__init__.py
scutil/_settings.py
scutil/scanpy_utils.py
scutil/_utils/__init__.py
scutil-0.1.1.dist-info/METADATA
scutil-0.1.1.dist-info/WHEEL
scutil-0.1.1.dist-info/RECORD
