Metadata-Version: 2.4
Name: scutil
Version: 0.1.1
Summary: A Python package utils to support scanpy usage
Project-URL: Homepage, https://github.com/brainfo/scutil
Project-URL: Issues, https://github.com/brainfo/scutil/issues
Author-email: brainfo <scilavisher@gmail.com>
Classifier: License :: OSI Approved :: MIT License
Classifier: Operating System :: OS Independent
Classifier: Programming Language :: Python :: 3
Requires-Python: >=3.8
Requires-Dist: scanpy>=1.9.8
Requires-Dist: seaborn>=0.13.2
Requires-Dist: zarr>=2.16.1
